LICENSE.txt
MANIFEST.in
README.txt
setup.py
lfc_portlets/__init__.py
lfc_portlets/models.py
lfc_portlets.egg-info/PKG-INFO
lfc_portlets.egg-info/SOURCES.txt
lfc_portlets.egg-info/dependency_links.txt
lfc_portlets.egg-info/not-zip-safe
lfc_portlets.egg-info/requires.txt
lfc_portlets.egg-info/top_level.txt